setup.py
dist_bingau/Binomialdistribution.py
dist_bingau/Gaussiandistribution.py
dist_bingau/Generaldistribution.py
dist_bingau/__init__.py
dist_bingau.egg-info/PKG-INFO
dist_bingau.egg-info/SOURCES.txt
dist_bingau.egg-info/dependency_links.txt
dist_bingau.egg-info/not-zip-safe
dist_bingau.egg-info/top_level.txt